examples/__init__.py
examples/cluster_create_example.py
examples/cluster_delete_example.py
examples/cluster_edit_example.py
examples/cluster_start_example.py
examples/cluster_stop_example.py
examples/drive_array_create_example.py
examples/drive_array_delete_example.py
examples/drive_array_edit_example.py
examples/drive_array_start_example.py
examples/drive_array_stop_example.py
examples/drive_snapshot_create_example.py
examples/drive_snapshot_rollback_example.py
examples/infrastructure_create_example.py
examples/infrastructure_delete_example.py
examples/infrastructure_deploy_example.py
examples/infrastructure_design_lock_set_example.py
examples/infrastructure_query_example.py
examples/infrastructures_example.py
examples/initialize_python_client.py
examples/instance_array_create_example.py
examples/instance_array_delete_example.py
examples/instance_array_edit_example.py
examples/instance_array_interface_attach_network_example.py
examples/instance_array_start_example.py
examples/instance_array_stop_example.py
metal_cloud_sdk/__init__.py
metal_cloud_sdk/api_exception.py
metal_cloud_sdk/api_exception_filter.py
metal_cloud_sdk/constants.py
metal_cloud_sdk/events.py
metal_cloud_sdk/clients/__init__.py
metal_cloud_sdk/clients/apacheds.py
metal_cloud_sdk/clients/api.py
metal_cloud_sdk/clients/developer.py
metal_cloud_sdk/clients/docs.py
metal_cloud_sdk/clients/extendedapi.py
metal_cloud_sdk/clients/guacamole.py
metal_cloud_sdk/clients/guest.py
metal_cloud_sdk/clients/hadoopdatalake.py
metal_cloud_sdk/clients/healthcheck.py
metal_cloud_sdk/clients/ipcbilling2.py
metal_cloud_sdk/clients/ipcordering2.py
metal_cloud_sdk/clients/ipcwebsite.py
metal_cloud_sdk/clients/kerberos.py
metal_cloud_sdk/clients/tests.py
metal_cloud_sdk/clients/vanillahostedscripts.py
metal_cloud_sdk/objects/__init__.py
metal_cloud_sdk/objects/ansiblebundle.py
metal_cloud_sdk/objects/appcloudera.py
metal_cloud_sdk/objects/appclouderainstance.py
metal_cloud_sdk/objects/appcontainerplatformkubernetes.py
metal_cloud_sdk-3.3.18.dist-info/LICENSE.md
metal_cloud_sdk-3.3.18.dist-info/METADATA
metal_cloud_sdk-3.3.18.dist-info/WHEEL
metal_cloud_sdk-3.3.18.dist-info/top_level.txt
metal_cloud_sdk-3.3.18.dist-info/RECORD
