Metadata-Version: 2.1
Name: metal-cloud-sdk
Version: 3.3.18
Summary: SDK for the Metal Cloud infrastructure
Home-page: https://gitlab.bigstep.com/generated-api-clients/metal-cloud-sdk-python2.x-private.git
Download-URL: https://gitlab.bigstep.com/generated-api-clients/metal-cloud-sdk-python2.x-private.git/tarball/3.3.18
Author: Bigstep Inc.
Author-email: bsiteam@bigstep.com
License: UNKNOWN
Keywords: metal,cloud,sdk
Platform: UNKNOWN
Classifier: Programming Language :: Python :: 2.7
Classifier: Programming Language :: Python :: 3.4
Classifier: Programming Language :: Python :: 3.6
License-File: LICENSE.md
Requires-Dist: jsonrpc2-base (==1.02)
Requires-Dist: future
